odin_fastcs/__init__.py
odin_fastcs/__main__.py
odin_fastcs/_version.py
odin_fastcs/http_connection.py
odin_fastcs/odin_controller.py
odin_fastcs/util.py
odin_fastcs-0.1.0.dist-info/LICENSE
odin_fastcs-0.1.0.dist-info/METADATA
odin_fastcs-0.1.0.dist-info/WHEEL
odin_fastcs-0.1.0.dist-info/entry_points.txt
odin_fastcs-0.1.0.dist-info/top_level.txt
odin_fastcs-0.1.0.dist-info/RECORD
