Metadata-Version: 2.1
Name: odin-fastcs
Version: 0.1.0
Summary: FastCS support for the Odin detector software framework
Author-email: James Souter <james.souter@diamond.ac.uk>, Gary Yendell <gary.yendell@diamond.ac.uk>
License: Apache License
Project-URL: GitHub, https://github.com/DiamondLightSource/odin-fastcs
Classifier: Development Status :: 3 - Alpha
Classifier: License :: OSI Approved :: Apache Software License
Classifier: Programming Language :: Python :: 3.11
Requires-Python: >=3.11
License-File: LICENSE
Requires-Dist: aiohttp
Requires-Dist: fastcs >=0.3.0
Provides-Extra: dev
Requires-Dist: copier ; extra == 'dev'
Requires-Dist: mypy ; extra == 'dev'
Requires-Dist: myst-parser ; extra == 'dev'
Requires-Dist: pipdeptree ; extra == 'dev'
Requires-Dist: pre-commit ; extra == 'dev'
Requires-Dist: pydata-sphinx-theme >=0.12 ; extra == 'dev'
Requires-Dist: pytest ; extra == 'dev'
Requires-Dist: pytest-cov ; extra == 'dev'
Requires-Dist: ruff ; extra == 'dev'
Requires-Dist: sphinx-autobuild ; extra == 'dev'
Requires-Dist: sphinx-copybutton ; extra == 'dev'
Requires-Dist: sphinx-design ; extra == 'dev'
Requires-Dist: tox-direct ; extra == 'dev'
Requires-Dist: types-mock ; extra == 'dev'
Requires-Dist: types-requests ; extra == 'dev'
